[
  {
    "name": "Froggy",
    "iconUrl": "images/froggy.jpg",
    "message": "Come visit me in Costa Rica!",
    "lat_long": [9.6660971, -85.0621176]
  },
  {
    "name": "Tim",
    "iconUrl": "images/tim_round.jpg",
    "message": "Hiking in the High Sierras!",
    "lat_long": [
      37.2320967,
      -118.8578716
    ]
  },

  {
    "name": "David",
    "iconUrl": "images/davidkantor.jpg",
    "message": "Hello everyone!",
    "lat_long": [
      40.666328,
      -73.553253
    ]
  },
  {
    "name": "Jack Keane",
    "iconUrl": "images/jkeane.jpg",
    "message": "Hello world",
    "lat_long": [39.640259, -106.370872],
    "year": "'22"
  },
  {
    "name": "Jacob Donoghue",
    "iconUrl": "images/jacobdonoghue.jpeg",
    "message": "Hello from Washington",
    "lat_long": [47.596233, -120.661476]
  }
]
